.hgignore
.hgtags
MANIFEST.in
README.txt
development.ini
setup.cfg
setup.py
test.ini
Twitabit.egg-info/PKG-INFO
Twitabit.egg-info/SOURCES.txt
Twitabit.egg-info/dependency_links.txt
Twitabit.egg-info/entry_points.txt
Twitabit.egg-info/paste_deploy_config.ini_tmpl
Twitabit.egg-info/paster_plugins.txt
Twitabit.egg-info/requires.txt
Twitabit.egg-info/top_level.txt
docs/index.txt
docs/writing.txt
ez_setup/README.txt
ez_setup/__init__.py
twitabit/__init__.py
twitabit/websetup.py
twitabit/config/__init__.py
twitabit/config/environment.py
twitabit/config/middleware.py
twitabit/config/routing.py
twitabit/controllers/__init__.py
twitabit/controllers/auth.py
twitabit/controllers/bits.py
twitabit/controllers/error.py
twitabit/controllers/template.py
twitabit/lib/__init__.py
twitabit/lib/app_globals.py
twitabit/lib/base.py
twitabit/lib/helpers.py
twitabit/model/__init__.py
twitabit/policy/__init__.py
twitabit/policy/twitabit_policy_001.py
twitabit/public/css/master.css
twitabit/public/css/reset-fonts-grids.css
twitabit/schema/__init__.py
twitabit/schema/twitabit_001.py
twitabit/templates/auth/__init__.py
twitabit/templates/auth/register.mako
twitabit/templates/auth/register_done.mako
twitabit/templates/auth/register_forms.mako
twitabit/templates/auth/register_name_taken.mako
twitabit/templates/auth/register_password_empty.mako
twitabit/templates/auth/register_password_mismatch.mako
twitabit/templates/auth/register_unnecessary.mako
twitabit/templates/auth/signin.mako
twitabit/templates/auth/signin_done.mako
twitabit/templates/auth/signin_fail.mako
twitabit/templates/auth/signout_done.mako
twitabit/templates/auth/signout_unnecessary.mako
twitabit/templates/bits/__init__.py
twitabit/templates/bits/all.mako
twitabit/templates/bits/post_forms.mako
twitabit/templates/bits/user.mako
twitabit/templates/bits/user_404.mako
twitabit/templates/layout/__init__.py
twitabit/templates/layout/standard.mako
twitabit/tests/__init__.py
twitabit/tests/test_models.py
twitabit/tests/functional/__init__.py
twitabit/tests/functional/test_auth.py
twitabit/tests/functional/test_bits.py
