Metadata-Version: 1.0
Name: Twitabit
Version: 1.0a1
Summary: Simple example application using Schevo
Home-page: http://schevo.org/wiki/Twitabit
Author: Orbtech, L.L.C. and contributors
Author-email: schevo@googlegroups.com
License: MIT
Platform: UNIX
Platform: Windows
Classifier: Intended Audience :: Developers
Classifier: License :: OSI Approved :: MIT License
Classifier: Operating System :: OS Independent
Classifier: Programming Language :: Python
Classifier: Topic :: Database :: Database Engines/Servers
Classifier: Topic :: Software Development :: Libraries :: Application Frameworks
